whttpx/Error.py
whttpx/__init__.py
whttpx/request.py
whttpx-0.0.7.dist-info/LICENSE
whttpx-0.0.7.dist-info/METADATA
whttpx-0.0.7.dist-info/WHEEL
whttpx-0.0.7.dist-info/top_level.txt
whttpx-0.0.7.dist-info/RECORD
